ada_auth.py
ada_auth-0.0.0.dist-info/METADATA
ada_auth-0.0.0.dist-info/WHEEL
ada_auth-0.0.0.dist-info/top_level.txt
ada_auth-0.0.0.dist-info/RECORD
